README.md
setup.py
dsnd_distributions_udacity_202004/Binomialdistribution.py
dsnd_distributions_udacity_202004/Gaussiandistribution.py
dsnd_distributions_udacity_202004/Generaldistribution.py
dsnd_distributions_udacity_202004/__init__.py
dsnd_distributions_udacity_202004.egg-info/PKG-INFO
dsnd_distributions_udacity_202004.egg-info/SOURCES.txt
dsnd_distributions_udacity_202004.egg-info/dependency_links.txt
dsnd_distributions_udacity_202004.egg-info/not-zip-safe
dsnd_distributions_udacity_202004.egg-info/top_level.txt