Metadata-Version: 1.0
Name: dsnd-distributions-udacity-202004
Version: 0.1
Summary: Gaussian and binomial distributions
Home-page: UNKNOWN
Author: Christoph Franzke
Author-email: UNKNOWN
License: UNKNOWN
Platform: UNKNOWN
